dolfen.py
dolfen-0.0.2.dist-info/METADATA
dolfen-0.0.2.dist-info/RECORD
dolfen-0.0.2.dist-info/WHEEL
dolfen-0.0.2.dist-info/top_level.txt
