Metadata-Version: 2.1
Name: dolfen
Version: 0.0.2
Summary: Downsampling Likelihood Function Estimation
Home-page: http://dolfen.readthedocs.org/
Download-URL: http://pypi.python.org/pypi/dolfen
Author: Jethro Linley
Author-email: jethro.linley@hotmail.co.uk
License: UNKNOWN
Platform: UNKNOWN
License-File: LICENSE.md
Requires-Dist: numpy (>=1.9)
Requires-Dist: scipy (>=0.16)
